piped_status_testing
